{
  "project_info": {
    "project_number": "19615854165",
    "project_id": "estatemap-481e4",
    "storage_bucket": "estatemap-481e4.appspot.com"
  },
  "client": [
    {
      "client_info": {
        "mobilesdk_app_id": "1:19615854165:android:cab57cf9bb5a2be0b3aedc",
        "android_client_info": {
          "package_name": "com.example.estatemap"
        }
      },
      "oauth_client": [],
      "api_key": [
        {
          "current_key": "AIzaSyBV9mz61-mS0fX3ipvnT5oBgg8gx2aCwjY"
        }
      ],
      "services": {
        "appinvite_service": {
          "other_platform_oauth_client": []
        }
      }
    }
  ],
  "configuration_version": "1"
}